lazympl/__init__.py
lazympl/figure.py
lazympl/plot.py
lazympl/py.typed
lazympl-0.2.0.dist-info/METADATA
lazympl-0.2.0.dist-info/WHEEL
lazympl-0.2.0.dist-info/licenses/LICENSE
lazympl-0.2.0.dist-info/RECORD
