Metadata-Version: 2.4
Name: lazympl
Version: 0.2.0
Summary: Lazy wrappers around matplotlib
Project-URL: homepage, https://github.com/amorison/lazympl
Author: Thomas Guillet
Author-email: Adrien Morison <adrien.morison@gmail.com>
Maintainer-email: Adrien Morison <adrien.morison@gmail.com>
License: MIT License
License-File: LICENSE
Classifier: Development Status :: 4 - Beta
Classifier: Intended Audience :: Developers
Classifier: License :: OSI Approved :: MIT License
Classifier: Programming Language :: Python :: 3 :: Only
Classifier: Programming Language :: Python :: 3.10
Classifier: Programming Language :: Python :: 3.11
Classifier: Programming Language :: Python :: 3.12
Classifier: Programming Language :: Python :: 3.13
Requires-Python: >=3.10
Requires-Dist: matplotlib>=3.10
